fastapi_cloudauth_lenient/__init__.py
fastapi_cloudauth_lenient/firebase_auth.py
fastapi_cloudauth_lenient/py.typed
fastapi_cloudauth_lenient-1.0.0.dist-info/METADATA
fastapi_cloudauth_lenient-1.0.0.dist-info/WHEEL
fastapi_cloudauth_lenient-1.0.0.dist-info/licenses/LICENSE
fastapi_cloudauth_lenient-1.0.0.dist-info/RECORD
