Metadata-Version: 2.4
Name: fastapi-cloudauth-lenient
Version: 1.0.0
Summary: Lenient Firebase authentication for FastAPI with configurable grace periods for time-based JWT claims
Project-URL: Homepage, https://github.com/CodifyIQ/fastapi-cloudauth-lenient
Project-URL: Repository, https://github.com/CodifyIQ/fastapi-cloudauth-lenient
Project-URL: Issues, https://github.com/CodifyIQ/fastapi-cloudauth-lenient/issues
Author-email: Eric Konieczny <eric.konieczny@codifyiq.com>
License: MIT
License-File: LICENSE
Keywords: auth,authentication,cloud-auth,fastapi,firebase,jwt,token-verification
Classifier: Development Status :: 5 - Production/Stable
Classifier: Framework :: FastAPI
Classifier: Intended Audience :: Developers
Classifier: License :: OSI Approved :: MIT License
Classifier: Operating System :: OS Independent
Classifier: Programming Language :: Python :: 3
Classifier: Programming Language :: Python :: 3.8
Classifier: Programming Language :: Python :: 3.9
Classifier: Programming Language :: Python :: 3.10
Classifier: Programming Language :: Python :: 3.11
Classifier: Programming Language :: Python :: 3.12
Classifier: Topic :: Internet :: WWW/HTTP :: HTTP Servers
Classifier: Topic :: Security
Classifier: Topic :: Software Development :: Libraries :: Python Modules
Requires-Python: >=3.8
Requires-Dist: fastapi-cloudauth>=0.4.0
Requires-Dist: loguru>=0.7.0
